pyside_callbacks/__init__.py
pyside_callbacks/py.typed
pyside_callbacks/pyside_callbacks.py
pyside_callbacks_mypy/plugin.py
pyside_callbacks_mypy/signals.toml
pyside_callbacks-0.1.1.dist-info/METADATA
pyside_callbacks-0.1.1.dist-info/WHEEL
pyside_callbacks-0.1.1.dist-info/top_level.txt
pyside_callbacks-0.1.1.dist-info/RECORD
