Metadata-Version: 2.1
Name: pyside-callbacks
Version: 0.1.1
Summary: Use decorators to simplify using UI creation flow for PySide
Author-email: Spencer Chang <spencer@sycee.xyz>
License: MIT
Project-URL: repository, https://github.com/schang412/pyside-callbacks
Classifier: Intended Audience :: Developers
Classifier: License :: OSI Approved :: MIT License
Classifier: Operating System :: OS Independent
Classifier: Programming Language :: Python
Classifier: Programming Language :: Python :: 3.10
Classifier: Programming Language :: Python :: 3.11
Classifier: Programming Language :: Python :: 3 :: Only
Classifier: Topic :: Software Development
Classifier: Typing :: Typed
Requires-Python: <3.12,>=3.10
